mfpml/__init__.py
mfpml/design_of_experiment/__init__.py
mfpml/design_of_experiment/multifidelity_samplers.py
mfpml/design_of_experiment/sampler.py
mfpml/design_of_experiment/singlefideliy_samplers.py
mfpml/design_of_experiment/space.py
mfpml/models/__init__.py
mfpml/models/basis_functions.py
mfpml/models/co_kriging.py
mfpml/models/gaussian_process.py
mfpml/models/gpr_base.py
mfpml/models/hierarchical_kriging.py
mfpml/models/kernels.py
mfpml/models/kriging.py
mfpml/models/mf_scale_kriging.py
mfpml/models/rbf.py
mfpml/optimization/__init__.py
mfpml/optimization/evolutionary_algorithms.py
mfpml/optimization/mf_acqusitions.py
mfpml/optimization/mfbo.py
mfpml/optimization/sf_acqusitions.py
mfpml/optimization/sfbo.py
mfpml/problems/__init__.py
mfpml/problems/functions.py
mfpml/problems/multifidelity_functions.py
mfpml/problems/multifidelity_reliability_analysis.py
mfpml/problems/singlefidelity_functions.py
mfpml/problems/singlefidelity_reliability_analysis.py
mfpml/reliablity_analysis/__init__.py
mfpml/reliablity_analysis/mf_active_learning_ra.py
mfpml/reliablity_analysis/mf_learning_functions.py
mfpml/reliablity_analysis/prob_evaluation.py
mfpml/reliablity_analysis/sf_active_learning_ra.py
mfpml/reliablity_analysis/sf_learning_functions.py
mfpml/reliablity_analysis/stopping_criteria.py
mfpml-1.0.0.dist-info/LICENSE
mfpml-1.0.0.dist-info/METADATA
mfpml-1.0.0.dist-info/WHEEL
mfpml-1.0.0.dist-info/top_level.txt
mfpml-1.0.0.dist-info/RECORD
