Metadata-Version: 2.1
Name: mfpml
Version: 1.0.0
Summary: Probabilistic machine learning methods
Home-page: https://github.com/JiaxiangYi96/mfpml
Author: Jiaxiang Yi
Author-email: J.Yi@tudelft.nl
License: MIT
Keywords: multi-fidelity machine learning,Bayesian Optimization
Classifier: License :: OSI Approved :: MIT License
Classifier: Development Status :: 5 - Production/Stable
Classifier: Intended Audience :: Developers
Classifier: Intended Audience :: Information Technology
Classifier: Intended Audience :: Science/Research
Classifier: Topic :: Scientific/Engineering :: Artificial Intelligence
Classifier: Topic :: Software Development :: Libraries :: Python Modules
Classifier: Programming Language :: Python :: 3.10
Classifier: Operating System :: Microsoft :: Windows
Classifier: Operating System :: POSIX :: Linux
Classifier: Operating System :: MacOS
Requires-Python: <3.12,>=3.10
License-File: LICENSE
Requires-Dist: matplotlib >=3.7.2
Requires-Dist: numpy >=1.25.1
Requires-Dist: scipy >=1.11.1
Requires-Dist: pandas >=2.0.3
Requires-Dist: scikit-learn >=1.3.0
